wobs/file_trace.py
wobs/observer.py
wobs/trackpoint.py
wobs/userInfo.py
wuying_guestos_observer_python-0.1.0.dist-info/METADATA
wuying_guestos_observer_python-0.1.0.dist-info/WHEEL
wuying_guestos_observer_python-0.1.0.dist-info/top_level.txt
wuying_guestos_observer_python-0.1.0.dist-info/RECORD
