Metadata-Version: 2.4
Name: wuying-guestos-observer-python
Version: 0.1.0
Summary: Add your description here
Requires-Python: >=3.9
Requires-Dist: opentelemetry-api>=1.36.0
Requires-Dist: opentelemetry-sdk>=1.36.0
Requires-Dist: pytest>=8.4.1
